m269_25j_marking_tool/__init__.py
m269_25j_marking_tool/_version.py
m269_25j_marking_tool/labextension/package.json
m269_25j_marking_tool/labextension/schemas/m269-25j-marking-tool/package.json.orig
m269_25j_marking_tool/labextension/schemas/m269-25j-marking-tool/plugin.json
m269_25j_marking_tool/labextension/static/509.1a0cd13f64ee44df834f.js
m269_25j_marking_tool/labextension/static/728.5f6524542dd95da2153e.js
m269_25j_marking_tool/labextension/static/remoteEntry.e1259a3dd66643b058f0.js
m269_25j_marking_tool/labextension/static/style.js
m269_25j_marking_tool/labextension/static/third-party-licenses.json
m269_25j_marking_tool-1.1.3.data/data/share/jupyter/labextensions/m269-25j-marking-tool/package.json
m269_25j_marking_tool-1.1.3.data/data/share/jupyter/labextensions/m269-25j-marking-tool/schemas/m269-25j-marking-tool/package.json.orig
m269_25j_marking_tool-1.1.3.data/data/share/jupyter/labextensions/m269-25j-marking-tool/schemas/m269-25j-marking-tool/plugin.json
m269_25j_marking_tool-1.1.3.data/data/share/jupyter/labextensions/m269-25j-marking-tool/static/509.1a0cd13f64ee44df834f.js
m269_25j_marking_tool-1.1.3.data/data/share/jupyter/labextensions/m269-25j-marking-tool/static/728.5f6524542dd95da2153e.js
m269_25j_marking_tool-1.1.3.data/data/share/jupyter/labextensions/m269-25j-marking-tool/static/remoteEntry.e1259a3dd66643b058f0.js
m269_25j_marking_tool-1.1.3.data/data/share/jupyter/labextensions/m269-25j-marking-tool/static/style.js
m269_25j_marking_tool-1.1.3.data/data/share/jupyter/labextensions/m269-25j-marking-tool/static/third-party-licenses.json
m269_25j_marking_tool-1.1.3.data/data/share/jupyter/labextensions/m269-25j-marking-tool/install.json
m269_25j_marking_tool-1.1.3.dist-info/METADATA
m269_25j_marking_tool-1.1.3.dist-info/WHEEL
m269_25j_marking_tool-1.1.3.dist-info/licenses/LICENSE
m269_25j_marking_tool-1.1.3.dist-info/RECORD
