Metadata-Version: 2.4
Name: m269_25j_marking_tool
Version: 1.1.3
Summary: A tutor marking tool for M269 in the 25J presentation
Project-URL: Homepage, https://github.com/dsa-ou/m269-25j-marking-tool
Project-URL: Bug Tracker, https://github.com/dsa-ou/m269-25j-marking-tool/issues
Project-URL: Repository, https://github.com/dsa-ou/m269-25j-marking-tool.git
Author-email: m269-25j-marking-tool <oli.howson@open.ac.uk>
License: BSD 3-Clause License
License-File: LICENSE
Keywords: jupyter,jupyterlab,jupyterlab-extension
Classifier: Framework :: Jupyter
Classifier: Framework :: Jupyter :: JupyterLab
Classifier: Framework :: Jupyter :: JupyterLab :: 4
Classifier: Framework :: Jupyter :: JupyterLab :: Extensions
Classifier: Framework :: Jupyter :: JupyterLab :: Extensions :: Prebuilt
Classifier: License :: OSI Approved :: BSD License
Classifier: Programming Language :: Python
Classifier: Programming Language :: Python :: 3
Classifier: Programming Language :: Python :: 3.9
Classifier: Programming Language :: Python :: 3.10
Classifier: Programming Language :: Python :: 3.11
Classifier: Programming Language :: Python :: 3.12
Classifier: Programming Language :: Python :: 3.13
Requires-Python: >=3.9
